{
  "frames": {
    "atlas_s0": {
      "frame": {
        "h": 51,
        "w": 17,
        "x": 0,
        "y": 0
      },
      "rotated": false,
      "sourceSize": {
        "h": 51,
        "w": 17
      },
      "spriteSourceSize": {
        "h": 51,
        "w": 17,
        "x": 0,
        "y": 0
      },
      "trimmed": false
    },
    "atlas_s1": {
      "frame": {
        "h": 48,
        "w": 18,
        "x": 17,
        "y": 0
      },
      "rotated": false,
      "sourceSize": {
        "h": 48,
        "w": 18
      },
      "spriteSourceSize": {
        "h": 48,
        "w": 18,
        "x": 0,
        "y": 0
      },
      "trimmed": false
    },
    "atlas_s10": {
      "frame": {
        "h": 48,
        "w": 17,
        "x": 171,
        "y": 0
      },
      "rotated": false,
      "sourceSize": {
        "h": 48,
        "w": 17
      },
      "spriteSourceSize": {
        "h": 48,
        "w": 17,
        "x": 0,
        "y": 0
      },
      "trimmed": false
    },
    "atlas_s11": {
      "frame": {
        "h": 48,
        "w": 17,
        "x": 188,
        "y": 0
      },
      "rotated": false,
      "sourceSize": {
        "h": 48,
        "w": 17
      },
      "spriteSourceSize": {
        "h": 48,
        "w": 17,
        "x": 0,
        "y": 0
      },
      "trimmed": false
    },
    "atlas_s2": {
      "frame": {
        "h": 48,
        "w": 17,
        "x": 35,
        "y": 0
      },
      "rotated": false,
      "sourceSize": {
        "h": 48,
        "w": 17
      },
      "spriteSourceSize": {
        "h": 48,
        "w": 17,
        "x": 0,
        "y": 0
      },
      "trimmed": false
    },
    "atlas_s3": {
      "frame": {
        "h": 48,
        "w": 17,
        "x": 52,
        "y": 0
      },
      "rotated": false,
      "sourceSize": {
        "h": 48,
        "w": 17
      },
      "spriteSourceSize": {
        "h": 48,
        "w": 17,
        "x": 0,
        "y": 0
      },
      "trimmed": false
    },
    "atlas_s4": {
      "frame": {
        "h": 48,
        "w": 17,
        "x": 69,
        "y": 0
      },
      "rotated": false,
      "sourceSize": {
        "h": 48,
        "w": 17
      },
      "spriteSourceSize": {
        "h": 48,
        "w": 17,
        "x": 0,
        "y": 0
      },
      "trimmed": false
    },
    "atlas_s5": {
      "frame": {
        "h": 48,
        "w": 17,
        "x": 86,
        "y": 0
      },
      "rotated": false,
      "sourceSize": {
        "h": 48,
        "w": 17
      },
      "spriteSourceSize": {
        "h": 48,
        "w": 17,
        "x": 0,
        "y": 0
      },
      "trimmed": false
    },
    "atlas_s6": {
      "frame": {
        "h": 48,
        "w": 17,
        "x": 103,
        "y": 0
      },
      "rotated": false,
      "sourceSize": {
        "h": 48,
        "w": 17
      },
      "spriteSourceSize": {
        "h": 48,
        "w": 17,
        "x": 0,
        "y": 0
      },
      "trimmed": false
    },
    "atlas_s7": {
      "frame": {
        "h": 48,
        "w": 17,
        "x": 120,
        "y": 0
      },
      "rotated": false,
      "sourceSize": {
        "h": 48,
        "w": 17
      },
      "spriteSourceSize": {
        "h": 48,
        "w": 17,
        "x": 0,
        "y": 0
      },
      "trimmed": false
    },
    "atlas_s8": {
      "frame": {
        "h": 48,
        "w": 17,
        "x": 137,
        "y": 0
      },
      "rotated": false,
      "sourceSize": {
        "h": 48,
        "w": 17
      },
      "spriteSourceSize": {
        "h": 48,
        "w": 17,
        "x": 0,
        "y": 0
      },
      "trimmed": false
    },
    "atlas_s9": {
      "frame": {
        "h": 48,
        "w": 17,
        "x": 154,
        "y": 0
      },
      "rotated": false,
      "sourceSize": {
        "h": 48,
        "w": 17
      },
      "spriteSourceSize": {
        "h": 48,
        "w": 17,
        "x": 0,
        "y": 0
      },
      "trimmed": false
    }
  },
  "meta": {
    "app": "Evil Invaders Atlas Builder",
    "format": "RGBA8888",
    "image": "atlas.png",
    "scale": "1",
    "size": {
      "h": 51,
      "w": 2048
    },
    "version": "1.0"
  }
}